turkishpyt/__init__.py
turkishpyt/core.py
turkishpyt-1.0.0.dist-info/METADATA
turkishpyt-1.0.0.dist-info/WHEEL
turkishpyt-1.0.0.dist-info/top_level.txt
turkishpyt-1.0.0.dist-info/RECORD
