Metadata-Version: 2.4
Name: turkishpyt
Version: 1.0.0
Summary: Türkçe Python kütüphanesi
License: MIT
Requires-Python: >=3.7
Dynamic: license
Dynamic: requires-python
Dynamic: summary
